Workbook

Sheet Revenue
A1: Month | B1: Budget Volume | C1: Actual Volume | D1: Avg Price | E1: Budget Revenue | F1: Actual Revenue
A2: Jan | B2: 1200 | C2: 1150 | D2: 95 | E2: =B2*D2 -> 114000 | F2: =C2*D2 -> 109250
A3: Feb | B3: 1250 | C3: 1120 | D3: 95 | E3: =B3*D3 -> 118750 | F3: =C3*D3 -> 106400
A4: Mar | B4: 1300 | C4: 1280 | D4: 95 | E4: =B4*D4 -> 123500 | F4: =C4*D4 -> 121600
A5: Apr | B5: 1100 | C5: 1000 | D5: 96 | E5: =B5*D5 -> 105600 | F5: =C5*D5 -> 96000
A6: May | B6: 1400 | C6: 1350 | D6: 96 | E6: =B6*D6 -> 134400 | F6: =C6*D6 -> 129600
A7: Jun | B7: 1550 | C7: 1580 | D7: 96 | E7: =B7*D7 -> 148800 | F7: =C7*D7 -> 151680
A8: Jul | B8: 1650 | C8: 1600 | D8: 97 | E8: =B8*D8 -> 160050 | F8: =C8*D8 -> 155200
A9: Aug | B9: 1700 | C9: 1750 | D9: 97 | E9: =B9*D9 -> 164900 | F9: =C9*D9 -> 169750
A10: Sep | B10: 1600 | C10: 1500 | D10: 98 | E10: =B10*D10 -> 156800 | F10: =C10*D10 -> 147000
A11: Oct | B11: 1650 | C11: 1620 | D11: 98 | E11: =B11*D11 -> 161700 | F11: =C11*D11 -> 158760
A12: Nov | B12: 1800 | C12: 1700 | D12: 99 | E12: =B12*D12 -> 178200 | F12: =C12*D12 -> 168300
A13: Dec | B13: 2000 | C13: 1850 | D13: 100 | E13: =B13*D13 -> 200000 | F13: =C13*D13 -> 185000

Sheet Budget OPEX
A1: Month | B1: Medical Supplies Budget | C1: Salaries Budget | D1: Rent Budget | E1: Utilities Budget | F1: Marketing Budget | G1: Other OPEX Budget | H1: Total Opex Budget
A2: Jan | B2: 18000 | C2: 42000 | D2: 15000 | E2: 3500 | F2: 5000 | G2: 2500 | H2: =SUM(B2:G2) -> 86000
A3: Feb | B3: 18250 | C3: 42000 | D3: 15000 | E3: 3550 | F3: 5000 | G3: 2550 | H3: =SUM(B3:G3) -> 86350
A4: Mar | B4: 18500 | C4: 42500 | D4: 15000 | E4: 3600 | F4: 5000 | G4: 2600 | H4: =SUM(B4:G4) -> 87200
A5: Apr | B5: 18750 | C5: 42500 | D5: 15000 | E5: 3650 | F5: 5050 | G5: 2650 | H5: =SUM(B5:G5) -> 87600
A6: May | B6: 19000 | C6: 43000 | D6: 15000 | E6: 3700 | F6: 5100 | G6: 2700 | H6: =SUM(B6:G6) -> 88500
A7: Jun | B7: 19250 | C7: 43500 | D7: 15000 | E7: 3750 | F7: 5150 | G7: 2750 | H7: =SUM(B7:G7) -> 89400
A8: Jul | B8: 19500 | C8: 44000 | D8: 15000 | E8: 3800 | F8: 5200 | G8: 2800 | H8: =SUM(B8:G8) -> 90300
A9: Aug | B9: 19750 | C9: 44500 | D9: 15000 | E9: 3850 | F9: 5250 | G9: 2850 | H9: =SUM(B9:G9) -> 91200
A10: Sep | B10: 20000 | C10: 45000 | D10: 15000 | E10: 3900 | F10: 5300 | G10: 2900 | H10: =SUM(B10:G10) -> 92100
A11: Oct | B11: 20250 | C11: 45000 | D11: 15000 | E11: 3950 | F11: 5350 | G11: 2950 | H11: =SUM(B11:G11) -> 92500
A12: Nov | B12: 20500 | C12: 45500 | D12: 15000 | E12: 4000 | F12: 5400 | G12: 3000 | H12: =SUM(B12:G12) -> 93400
A13: Dec | B13: 20750 | C13: 46000 | D13: 15000 | E13: 4050 | F13: 5450 | G13: 3050 | H13: =SUM(B13:G13) -> 94300

Sheet Actual OPEX
A1: Month | B1: Medical Supplies | C1: Salaries | D1: Rent | E1: Utilities | F1: Marketing | G1: Other OPEX | H1: Total OPEX
A2: Jan | B2: 18000 | C2: 42000 | D2: 15000 | E2: 3500 | F2: 5000 | G2: 2500 | H2: 86000
A3: Feb | B3: 18500 | C3: 42000 | D3: 15000 | E3: 3550 | F3: 5000 | G3: 2600 | H3: 86650
A4: Mar | B4: 19000 | C4: 43000 | D4: 15000 | E4: 3600 | F4: 5000 | G4: 2700 | H4: 88300
A5: Apr | B5: 19500 | C5: 43000 | D5: 15000 | E5: 3800 | F5: 5100 | G5: 2800 | H5: 89200
A6: May | B6: 21000 | C6: 44500 | D6: 15000 | E6: 4200 | F6: 5300 | G6: 3000 | H6: 93000
A7: Jun | B7: 21500 | C7: 45000 | D7: 15000 | E7: 4300 | F7: 5400 | G7: 3100 | H7: 94300
A8: Jul | B8: 22000 | C8: 46000 | D8: 15000 | E8: 4500 | F8: 5500 | G8: 3300 | H8: 96300
A9: Aug | B9: 22500 | C9: 46500 | D9: 15000 | E9: 4800 | F9: 5700 | G9: 3500 | H9: 98000
A10: Sep | B10: 23000 | C10: 47000 | D10: 15000 | E10: 5000 | F10: 5900 | G10: 3600 | H10: 99500
A11: Oct | B11: 25500 | C11: 47000 | D11: 15000 | E11: 5500 | F11: 6200 | G11: 3900 | H11: 103100
A12: Nov | B12: 26000 | C12: 47500 | D12: 15000 | E12: 5600 | F12: 6500 | G12: 4100 | H12: 104700
A13: Dec | B13: 27000 | C13: 48000 | D13: 15000 | E13: 5800 | F13: 6900 | G13: 4200 | H13: 106900

Sheet Working Capital
A1: Month | B1: Receivables | C1: Payables | D1: Inventory
A2: Jan | B2: 33000 | C2: 29000 | D2: 12000
A3: Feb | B3: 33800 | C3: 29500 | D3: 12500
A4: Mar | B4: 35000 | C4: 30000 | D4: 13000
A5: Apr | B5: 34200 | C5: 31000 | D5: 13500
A6: May | B6: 36900 | C6: 31500 | D6: 16500
A7: Jun | B7: 39300 | C7: 32000 | D7: 17000
A8: Jul | B8: 40200 | C8: 33000 | D8: 17500
A9: Aug | B9: 41300 | C9: 34000 | D9: 18000
A10: Sep | B10: 42800 | C10: 34500 | D10: 20000
A11: Oct | B11: 43900 | C11: 35000 | D11: 21000
A12: Nov | B12: 50000 | C12: 35500 | D12: 22000
A13: Dec | B13: 47000 | C13: 36000 | D13: 23000

Sheet Receivables Ageing
A1: Month | B1: <30 | C1: 31-60 | D1: 61-90 | E1: >90 | F1: Total Receivables
A2: Jan | B2: 20000 | C2: 7000 | D2: 3500 | E2: 2500 | F2: 33000
A3: Feb | B3: 20500 | C3: 7100 | D3: 3600 | E3: 2600 | F3: 33800
A4: Mar | B4: 21000 | C4: 7200 | D4: 3800 | E4: 3000 | F4: 35000
A5: Apr | B5: 18000 | C5: 8500 | D5: 4500 | E5: 3200 | F5: 34200
A6: May | B6: 19500 | C6: 8600 | D6: 5200 | E6: 3600 | F6: 36900
A7: Jun | B7: 20500 | C7: 8800 | D7: 5600 | E7: 4400 | F7: 39300
A8: Jul | B8: 21000 | C8: 9000 | D8: 5900 | E8: 4300 | F8: 40200
A9: Aug | B9: 21500 | C9: 9200 | D9: 6100 | E9: 4500 | F9: 41300
A10: Sep | B10: 21800 | C10: 9500 | D10: 6500 | E10: 5000 | F10: 42800
A11: Oct | B11: 22000 | C11: 9700 | D11: 7000 | E11: 5200 | F11: 43900
A12: Nov | B12: 22500 | C12: 10000 | D12: 7500 | E12: 5600 | F12: 45600
A13: Dec | B13: 23000 | C13: 10200 | D13: 7800 | E13: 6000 | F13: 47000

Sheet Loan Schedule
A1: Month | B1: Opening | C1: Interest | D1: Principal | E1: Closing
A2: Jan | B2: 120000 | C2: 700 | D2: 5000 | E2: 115000
A3: Feb | B3: 115000 | C3: 670.83 | D3: 5000 | E3: 110000
A4: Mar | B4: 110000 | C4: 641.67 | D4: 5000 | E4: 105000
A5: Apr | B5: 105000 | C5: 612.5 | D5: 5000 | E5: 100000
A6: May | B6: 100000 | C6: 583.33 | D6: 5000 | E6: 95000
A7: Jun | B7: 95000 | C7: 554.17 | D7: 5000 | E7: 90000
A8: Jul | B8: 90000 | C8: 525 | D8: 5000 | E8: 85000
A9: Aug | B9: 85000 | C9: 495.83 | D9: 5000 | E9: 80000
A10: Sep | B10: 80000 | C10: 466.67 | D10: 5000 | E10: 75000
A11: Oct | B11: 75000 | C11: 437.5 | D11: 5000 | E11: 70000
A12: Nov | B12: 70000 | C12: 408.33 | D12: 5000 | E12: 65000
A13: Dec | B13: 65000 | C13: 379.17 | D13: 5000 | E13: 60000

Sheet CAPEX
A1: Month | B1: CAPEX
A2: Mar | B2: 25000
A3: Sep | B3: 30000
A4: Nov | B4: 25000

Sheet Assumptions
A2: Opening Cash Balance | C2: 85000
A3: Depreciation per month | C3: 833.33
A5: Scenario drivers
C6: Volume | D6: Price | E6: Opex
B7: Best | C7: 10 | D7: 5 | E7: 2
B8: Base | C8: 0 | D8: 0 | E8: 4
B9: Worst | C9: -15 | D9: -5 | E9: 8
A14: Note
A15: Forecasting in this project is delivered through the budgeting model, the 12-month cashflow forecast, and scenario-based forecasting.
A16: The budget represents the base-case forecast, the cashflow model projects future liquidity, and the scenario model evaluates alternative future outcomes under different assumptions

Sheet P&L Model
A1: Month | B1: Forecast Revenue | C1: Actual Revenue | D1: Forecast Opex | E1: Actual Opex | F1: Forecast Profit | G1: Actual Profit | H1: Forecast Margin | I1: Actual Margin | J1: Interest | K1: Forecast Net Profit
A2: Jan | B2: =INDEX(Revenue!E:E,MATCH(A2,Revenue!A:A, 0)) -> 114000 | C2: =INDEX(Revenue!F:F,MATCH(A2,Revenue!A:A, 0)) -> 109250 | D2: =INDEX('Budget OPEX'!H:H,MATCH(A2,'Budget OPEX'!A:A, 0)) -> 86000 | E2: =INDEX('Actual OPEX'!H:H,MATCH(A2,'Actual OPEX'!A:A, 0)) -> 86000 | F2: =B2-D2 -> 28000 | G2: =C2-E2 -> 23250 | H2: =F2/B2 -> 0.24561404 | I2: =G2/C2 -> 0.21281465 | J2: =INDEX('Loan Schedule'!C:C,MATCH(A2,'Loan Schedule'!A:A, 0)) -> 700 | K2: =F2-J2 -> 27300
A3: Feb | B3: =INDEX(Revenue!E:E,MATCH(A3,Revenue!A:A, 0)) -> 118750 | C3: =INDEX(Revenue!F:F,MATCH(A3,Revenue!A:A, 0)) -> 106400 | D3: =INDEX('Budget OPEX'!H:H,MATCH(A3,'Budget OPEX'!A:A, 0)) -> 86350 | E3: =INDEX('Actual OPEX'!H:H,MATCH(A3,'Actual OPEX'!A:A, 0)) -> 86650 | F3: =B3-D3 -> 32400 | G3: =C3-E3 -> 19750 | H3: =F3/B3 -> 0.27284211 | I3: =G3/C3 -> 0.1856203 | J3: =INDEX('Loan Schedule'!C:C,MATCH(A3,'Loan Schedule'!A:A, 0)) -> 670.83 | K3: =F3-J3 -> 31729.17
A4: Mar | B4: =INDEX(Revenue!E:E,MATCH(A4,Revenue!A:A, 0)) -> 123500 | C4: =INDEX(Revenue!F:F,MATCH(A4,Revenue!A:A, 0)) -> 121600 | D4: =INDEX('Budget OPEX'!H:H,MATCH(A4,'Budget OPEX'!A:A, 0)) -> 87200 | E4: =INDEX('Actual OPEX'!H:H,MATCH(A4,'Actual OPEX'!A:A, 0)) -> 88300 | F4: =B4-D4 -> 36300 | G4: =C4-E4 -> 33300 | H4: =F4/B4 -> 0.29392713 | I4: =G4/C4 -> 0.27384868 | J4: =INDEX('Loan Schedule'!C:C,MATCH(A4,'Loan Schedule'!A:A, 0)) -> 641.67 | K4: =F4-J4 -> 35658.33
A5: Apr | B5: =INDEX(Revenue!E:E,MATCH(A5,Revenue!A:A, 0)) -> 105600 | C5: =INDEX(Revenue!F:F,MATCH(A5,Revenue!A:A, 0)) -> 96000 | D5: =INDEX('Budget OPEX'!H:H,MATCH(A5,'Budget OPEX'!A:A, 0)) -> 87600 | E5: =INDEX('Actual OPEX'!H:H,MATCH(A5,'Actual OPEX'!A:A, 0)) -> 89200 | F5: =B5-D5 -> 18000 | G5: =C5-E5 -> 6800 | H5: =F5/B5 -> 0.17045455 | I5: =G5/C5 -> 0.070833333 | J5: =INDEX('Loan Schedule'!C:C,MATCH(A5,'Loan Schedule'!A:A, 0)) -> 612.5 | K5: =F5-J5 -> 17387.5
A6: May | B6: =INDEX(Revenue!E:E,MATCH(A6,Revenue!A:A, 0)) -> 134400 | C6: =INDEX(Revenue!F:F,MATCH(A6,Revenue!A:A, 0)) -> 129600 | D6: =INDEX('Budget OPEX'!H:H,MATCH(A6,'Budget OPEX'!A:A, 0)) -> 88500 | E6: =INDEX('Actual OPEX'!H:H,MATCH(A6,'Actual OPEX'!A:A, 0)) -> 93000 | F6: =B6-D6 -> 45900 | G6: =C6-E6 -> 36600 | H6: =F6/B6 -> 0.34151786 | I6: =G6/C6 -> 0.28240741 | J6: =INDEX('Loan Schedule'!C:C,MATCH(A6,'Loan Schedule'!A:A, 0)) -> 583.33 | K6: =F6-J6 -> 45316.67
A7: Jun | B7: =INDEX(Revenue!E:E,MATCH(A7,Revenue!A:A, 0)) -> 148800 | C7: =INDEX(Revenue!F:F,MATCH(A7,Revenue!A:A, 0)) -> 151680 | D7: =INDEX('Budget OPEX'!H:H,MATCH(A7,'Budget OPEX'!A:A, 0)) -> 89400 | E7: =INDEX('Actual OPEX'!H:H,MATCH(A7,'Actual OPEX'!A:A, 0)) -> 94300 | F7: =B7-D7 -> 59400 | G7: =C7-E7 -> 57380 | H7: =F7/B7 -> 0.39919355 | I7: =G7/C7 -> 0.37829641 | J7: =INDEX('Loan Schedule'!C:C,MATCH(A7,'Loan Schedule'!A:A, 0)) -> 554.17 | K7: =F7-J7 -> 58845.83
A8: Jul | B8: =INDEX(Revenue!E:E,MATCH(A8,Revenue!A:A, 0)) -> 160050 | C8: =INDEX(Revenue!F:F,MATCH(A8,Revenue!A:A, 0)) -> 155200 | D8: =INDEX('Budget OPEX'!H:H,MATCH(A8,'Budget OPEX'!A:A, 0)) -> 90300 | E8: =INDEX('Actual OPEX'!H:H,MATCH(A8,'Actual OPEX'!A:A, 0)) -> 96300 | F8: =B8-D8 -> 69750 | G8: =C8-E8 -> 58900 | H8: =F8/B8 -> 0.43580131 | I8: =G8/C8 -> 0.37951031 | J8: =INDEX('Loan Schedule'!C:C,MATCH(A8,'Loan Schedule'!A:A, 0)) -> 525 | K8: =F8-J8 -> 69225
A9: Aug | B9: =INDEX(Revenue!E:E,MATCH(A9,Revenue!A:A, 0)) -> 164900 | C9: =INDEX(Revenue!F:F,MATCH(A9,Revenue!A:A, 0)) -> 169750 | D9: =INDEX('Budget OPEX'!H:H,MATCH(A9,'Budget OPEX'!A:A, 0)) -> 91200 | E9: =INDEX('Actual OPEX'!H:H,MATCH(A9,'Actual OPEX'!A:A, 0)) -> 98000 | F9: =B9-D9 -> 73700 | G9: =C9-E9 -> 71750 | H9: =F9/B9 -> 0.44693754 | I9: =G9/C9 -> 0.42268041 | J9: =INDEX('Loan Schedule'!C:C,MATCH(A9,'Loan Schedule'!A:A, 0)) -> 495.83 | K9: =F9-J9 -> 73204.17
A10: Sep | B10: =INDEX(Revenue!E:E,MATCH(A10,Revenue!A:A, 0)) -> 156800 | C10: =INDEX(Revenue!F:F,MATCH(A10,Revenue!A:A, 0)) -> 147000 | D10: =INDEX('Budget OPEX'!H:H,MATCH(A10,'Budget OPEX'!A:A, 0)) -> 92100 | E10: =INDEX('Actual OPEX'!H:H,MATCH(A10,'Actual OPEX'!A:A, 0)) -> 99500 | F10: =B10-D10 -> 64700 | G10: =C10-E10 -> 47500 | H10: =F10/B10 -> 0.41262755 | I10: =G10/C10 -> 0.32312925 | J10: =INDEX('Loan Schedule'!C:C,MATCH(A10,'Loan Schedule'!A:A, 0)) -> 466.67 | K10: =F10-J10 -> 64233.33
A11: Oct | B11: =INDEX(Revenue!E:E,MATCH(A11,Revenue!A:A, 0)) -> 161700 | C11: =INDEX(Revenue!F:F,MATCH(A11,Revenue!A:A, 0)) -> 158760 | D11: =INDEX('Budget OPEX'!H:H,MATCH(A11,'Budget OPEX'!A:A, 0)) -> 92500 | E11: =INDEX('Actual OPEX'!H:H,MATCH(A11,'Actual OPEX'!A:A, 0)) -> 103100 | F11: =B11-D11 -> 69200 | G11: =C11-E11 -> 55660 | H11: =F11/B11 -> 0.427953 | I11: =G11/C11 -> 0.35059209 | J11: =INDEX('Loan Schedule'!C:C,MATCH(A11,'Loan Schedule'!A:A, 0)) -> 437.5 | K11: =F11-J11 -> 68762.5
A12: Nov | B12: =INDEX(Revenue!E:E,MATCH(A12,Revenue!A:A, 0)) -> 178200 | C12: =INDEX(Revenue!F:F,MATCH(A12,Revenue!A:A, 0)) -> 168300 | D12: =INDEX('Budget OPEX'!H:H,MATCH(A12,'Budget OPEX'!A:A, 0)) -> 93400 | E12: =INDEX('Actual OPEX'!H:H,MATCH(A12,'Actual OPEX'!A:A, 0)) -> 104700 | F12: =B12-D12 -> 84800 | G12: =C12-E12 -> 63600 | H12: =F12/B12 -> 0.47586981 | I12: =G12/C12 -> 0.37789661 | J12: =INDEX('Loan Schedule'!C:C,MATCH(A12,'Loan Schedule'!A:A, 0)) -> 408.33 | K12: =F12-J12 -> 84391.67
A13: Dec | B13: =INDEX(Revenue!E:E,MATCH(A13,Revenue!A:A, 0)) -> 200000 | C13: =INDEX(Revenue!F:F,MATCH(A13,Revenue!A:A, 0)) -> 185000 | D13: =INDEX('Budget OPEX'!H:H,MATCH(A13,'Budget OPEX'!A:A, 0)) -> 94300 | E13: =INDEX('Actual OPEX'!H:H,MATCH(A13,'Actual OPEX'!A:A, 0)) -> 106900 | F13: =B13-D13 -> 105700 | G13: =C13-E13 -> 78100 | H13: =F13/B13 -> 0.5285 | I13: =G13/C13 -> 0.42216216 | J13: =INDEX('Loan Schedule'!C:C,MATCH(A13,'Loan Schedule'!A:A, 0)) -> 379.17 | K13: =F13-J13 -> 105320.83

Sheet Variance
A1: Month | B1: Revenue Variance | C1: Revenue Variance% | D1: Opex Variance | E1: Opex Variance % | F1: Profit Variance | G1: Favourable/Unfavourable
A2: Jan | B2: =INDEX('P&L Model'!C:C,MATCH(A2,'P&L Model'!A:A, 0))-INDEX('P&L Model'!B:B,MATCH(A2,'P&L Model'!A:A,0)) -> -4750 | C2: =B2/'P&L Model'!B2 -> -0.041666667 | D2: =INDEX('P&L Model'!E:E,MATCH(A2,'P&L Model'!A:A,0))-INDEX('P&L Model'!D:D,MATCH(A2,'P&L Model'!A:A,0)) -> 0 | E2: =D2/'P&L Model'!D2 -> 0 | F2: =INDEX('P&L Model'!G:G,MATCH(A2,'P&L Model'!A:A,0))-INDEX('P&L Model'!F:F,MATCH(A2,'P&L Model'!A:A,0)) -> -4750 | G2: =IF(AND(B2>=0,D2<=0),"F","U") -> U
A3: Feb | B3: =INDEX('P&L Model'!C:C,MATCH(A3,'P&L Model'!A:A, 0))-INDEX('P&L Model'!B:B,MATCH(A3,'P&L Model'!A:A,0)) -> -12350 | C3: =B3/'P&L Model'!B3 -> -0.104 | D3: =INDEX('P&L Model'!E:E,MATCH(A3,'P&L Model'!A:A, 0))-INDEX('P&L Model'!D:D,MATCH(A3,'P&L Model'!A:A, 0)) -> 300 | E3: =D3/'P&L Model'!D3 -> 0.0034742328 | F3: =INDEX('P&L Model'!G:G,MATCH(A3,'P&L Model'!A:A,0))-INDEX('P&L Model'!F:F,MATCH(A3,'P&L Model'!A:A,0)) -> -12650 | G3: =IF(AND(B3>=0,D3<=0),"F","U") -> U
A4: Mar | B4: =INDEX('P&L Model'!C:C,MATCH(A4,'P&L Model'!A:A, 0))-INDEX('P&L Model'!B:B,MATCH(A4,'P&L Model'!A:A,0)) -> -1900 | C4: =B4/'P&L Model'!B4 -> -0.015384615 | D4: =INDEX('P&L Model'!E:E,MATCH(A4,'P&L Model'!A:A, 0))-INDEX('P&L Model'!D:D,MATCH(A4,'P&L Model'!A:A, 0)) -> 1100 | E4: =D4/'P&L Model'!D4 -> 0.012614679 | F4: =INDEX('P&L Model'!G:G,MATCH(A4,'P&L Model'!A:A,0))-INDEX('P&L Model'!F:F,MATCH(A4,'P&L Model'!A:A,0)) -> -3000 | G4: =IF(AND(B4>=0,D4<=0),"F","U") -> U
A5: Apr | B5: =INDEX('P&L Model'!C:C,MATCH(A5,'P&L Model'!A:A, 0))-INDEX('P&L Model'!B:B,MATCH(A5,'P&L Model'!A:A,0)) -> -9600 | C5: =B5/'P&L Model'!B5 -> -0.090909091 | D5: =INDEX('P&L Model'!E:E,MATCH(A5,'P&L Model'!A:A, 0))-INDEX('P&L Model'!D:D,MATCH(A5,'P&L Model'!A:A, 0)) -> 1600 | E5: =D5/'P&L Model'!D5 -> 0.01826484 | F5: =INDEX('P&L Model'!G:G,MATCH(A5,'P&L Model'!A:A,0))-INDEX('P&L Model'!F:F,MATCH(A5,'P&L Model'!A:A,0)) -> -11200 | G5: =IF(AND(B5>=0,D5<=0),"F","U") -> U
A6: May | B6: =INDEX('P&L Model'!C:C,MATCH(A6,'P&L Model'!A:A, 0))-INDEX('P&L Model'!B:B,MATCH(A6,'P&L Model'!A:A,0)) -> -4800 | C6: =B6/'P&L Model'!B6 -> -0.035714286 | D6: =INDEX('P&L Model'!E:E,MATCH(A6,'P&L Model'!A:A, 0))-INDEX('P&L Model'!D:D,MATCH(A6,'P&L Model'!A:A, 0)) -> 4500 | E6: =D6/'P&L Model'!D6 -> 0.050847458 | F6: =INDEX('P&L Model'!G:G,MATCH(A6,'P&L Model'!A:A,0))-INDEX('P&L Model'!F:F,MATCH(A6,'P&L Model'!A:A,0)) -> -9300 | G6: =IF(AND(B6>=0,D6<=0),"F","U") -> U
A7: Jun | B7: =INDEX('P&L Model'!C:C,MATCH(A7,'P&L Model'!A:A, 0))-INDEX('P&L Model'!B:B,MATCH(A7,'P&L Model'!A:A,0)) -> 2880 | C7: =B7/'P&L Model'!B7 -> 0.019354839 | D7: =INDEX('P&L Model'!E:E,MATCH(A7,'P&L Model'!A:A, 0))-INDEX('P&L Model'!D:D,MATCH(A7,'P&L Model'!A:A, 0)) -> 4900 | E7: =D7/'P&L Model'!D7 -> 0.054809843 | F7: =INDEX('P&L Model'!G:G,MATCH(A7,'P&L Model'!A:A,0))-INDEX('P&L Model'!F:F,MATCH(A7,'P&L Model'!A:A,0)) -> -2020 | G7: =IF(AND(B7>=0,D7<=0),"F","U") -> U
A8: Jul | B8: =INDEX('P&L Model'!C:C,MATCH(A8,'P&L Model'!A:A, 0))-INDEX('P&L Model'!B:B,MATCH(A8,'P&L Model'!A:A,0)) -> -4850 | C8: =B8/'P&L Model'!B8 -> -0.03030303 | D8: =INDEX('P&L Model'!E:E,MATCH(A8,'P&L Model'!A:A, 0))-INDEX('P&L Model'!D:D,MATCH(A8,'P&L Model'!A:A, 0)) -> 6000 | E8: =D8/'P&L Model'!D8 -> 0.066445183 | F8: =INDEX('P&L Model'!G:G,MATCH(A8,'P&L Model'!A:A,0))-INDEX('P&L Model'!F:F,MATCH(A8,'P&L Model'!A:A,0)) -> -10850 | G8: =IF(AND(B8>=0,D8<=0),"F","U") -> U
A9: Aug | B9: =INDEX('P&L Model'!C:C,MATCH(A9,'P&L Model'!A:A, 0))-INDEX('P&L Model'!B:B,MATCH(A9,'P&L Model'!A:A,0)) -> 4850 | C9: =B9/'P&L Model'!B9 -> 0.029411765 | D9: =INDEX('P&L Model'!E:E,MATCH(A9,'P&L Model'!A:A, 0))-INDEX('P&L Model'!D:D,MATCH(A9,'P&L Model'!A:A, 0)) -> 6800 | E9: =D9/'P&L Model'!D9 -> 0.074561404 | F9: =INDEX('P&L Model'!G:G,MATCH(A9,'P&L Model'!A:A,0))-INDEX('P&L Model'!F:F,MATCH(A9,'P&L Model'!A:A,0)) -> -1950 | G9: =IF(AND(B9>=0,D9<=0),"F","U") -> U
A10: Sep | B10: =INDEX('P&L Model'!C:C,MATCH(A10,'P&L Model'!A:A, 0))-INDEX('P&L Model'!B:B,MATCH(A10,'P&L Model'!A:A,0)) -> -9800 | C10: =B10/'P&L Model'!B10 -> -0.0625 | D10: =INDEX('P&L Model'!E:E,MATCH(A10,'P&L Model'!A:A, 0))-INDEX('P&L Model'!D:D,MATCH(A10,'P&L Model'!A:A, 0)) -> 7400 | E10: =D10/'P&L Model'!D10 -> 0.080347448 | F10: =INDEX('P&L Model'!G:G,MATCH(A10,'P&L Model'!A:A,0))-INDEX('P&L Model'!F:F,MATCH(A10,'P&L Model'!A:A,0)) -> -17200 | G10: =IF(AND(B10>=0,D10<=0),"F","U") -> U
A11: Oct | B11: =INDEX('P&L Model'!C:C,MATCH(A11,'P&L Model'!A:A, 0))-INDEX('P&L Model'!B:B,MATCH(A11,'P&L Model'!A:A,0)) -> -2940 | C11: =B11/'P&L Model'!B11 -> -0.018181818 | D11: =INDEX('P&L Model'!E:E,MATCH(A11,'P&L Model'!A:A, 0))-INDEX('P&L Model'!D:D,MATCH(A11,'P&L Model'!A:A, 0)) -> 10600 | E11: =D11/'P&L Model'!D11 -> 0.11459459 | F11: =INDEX('P&L Model'!G:G,MATCH(A11,'P&L Model'!A:A,0))-INDEX('P&L Model'!F:F,MATCH(A11,'P&L Model'!A:A,0)) -> -13540 | G11: =IF(AND(B11>=0,D11<=0),"F","U") -> U
A12: Nov | B12: =INDEX('P&L Model'!C:C,MATCH(A12,'P&L Model'!A:A, 0))-INDEX('P&L Model'!B:B,MATCH(A12,'P&L Model'!A:A,0)) -> -9900 | C12: =B12/'P&L Model'!B12 -> -0.055555556 | D12: =INDEX('P&L Model'!E:E,MATCH(A12,'P&L Model'!A:A, 0))-INDEX('P&L Model'!D:D,MATCH(A12,'P&L Model'!A:A, 0)) -> 11300 | E12: =D12/'P&L Model'!D12 -> 0.12098501 | F12: =INDEX('P&L Model'!G:G,MATCH(A12,'P&L Model'!A:A,0))-INDEX('P&L Model'!F:F,MATCH(A12,'P&L Model'!A:A,0)) -> -21200 | G12: =IF(AND(B12>=0,D12<=0),"F","U") -> U
A13: Dec | B13: =INDEX('P&L Model'!C:C,MATCH(A13,'P&L Model'!A:A, 0))-INDEX('P&L Model'!B:B,MATCH(A13,'P&L Model'!A:A,0)) -> -15000 | C13: =B13/'P&L Model'!B13 -> -0.075 | D13: =INDEX('P&L Model'!E:E,MATCH(A13,'P&L Model'!A:A, 0))-INDEX('P&L Model'!D:D,MATCH(A13,'P&L Model'!A:A, 0)) -> 12600 | E13: =D13/'P&L Model'!D13 -> 0.13361612 | F13: =INDEX('P&L Model'!G:G,MATCH(A13,'P&L Model'!A:A,0))-INDEX('P&L Model'!F:F,MATCH(A13,'P&L Model'!A:A,0)) -> -27600 | G13: =IF(AND(B13>=0,D13<=0),"F","U") -> U

Sheet Scenario
F1: Selected Volume | G1: Selected Price | H1: Selected Opex
F2: =INDEX(B7:B9,MATCH(B3,A7:A9,0)) -> -0.15 | G2: =INDEX(C7:C9,MATCH(B3,A7:A9,0)) -> -0.05 | H2: =INDEX(D7:D9,MATCH(B3,A7:A9,0)) -> 0.08
A3: Scenario | B3: Worst
B5: Scenario Forecast Comparison (12-month Outlook)
A6: Scenario | B6: Volume | C6: Price | D6: Opex
A7: Best | B7: 0.1 | C7: 0.05 | D7: 0.02
A8: Base | B8: 0 | C8: 0 | D8: 0.04
A9: Worst | B9: -0.15 | C9: -0.05 | D9: 0.08
A13: Month | B13: Base Revenue | C13: Scenario Revenue | D13: Base Opex | E13: Scenario OPEX | F13: Scenario Profit | G13: Interest | H13: Net Profit | I13: Depreciation | J13: WC net | K13: Scenario Operating CF
A14: Jan | B14: =INDEX('P&L Model'!B:B,MATCH(A14,'P&L Model'!A:A,0)) -> 114000 | C14: =B14*(1+$F$2)*(1+$G$2) -> 92055 | D14: =INDEX('P&L Model'!D:D,MATCH(A14,'P&L Model'!A:A,0)) -> 86000 | E14: =D14*(1+$H$2) -> 92880 | F14: =C14-E14 -> -825 | G14: =INDEX('P&L Model'!J:J,MATCH(A14,'P&L Model'!A:A,0)) -> 700 | H14: =F14-G14 -> -1525 | I14: =Assumptions!$C$3 -> 833.33 | J14: =INDEX('Cashflow Forecast'!G:G,MATCH(A14,'Cashflow Forecast'!A:A,0)) -> 0 | K14: =H14+I14+J14 -> -691.67
A15: Feb | B15: =INDEX('P&L Model'!B:B,MATCH(A15,'P&L Model'!A:A,0)) -> 118750 | C15: =B15*(1+$F$2)*(1+$G$2) -> 95890.625 | D15: =INDEX('P&L Model'!D:D,MATCH(A15,'P&L Model'!A:A,0)) -> 86350 | E15: =D15*(1+$H$2) -> 93258 | F15: =C15-E15 -> 2632.625 | G15: =INDEX('P&L Model'!J:J,MATCH(A15,'P&L Model'!A:A,0)) -> 670.83 | H15: =F15-G15 -> 1961.795 | I15: =Assumptions!$C$3 -> 833.33 | J15: =INDEX('Cashflow Forecast'!G:G,MATCH(A15,'Cashflow Forecast'!A:A,0)) -> -800 | K15: =H15+I15+J15 -> 1995.125
A16: Mar | B16: =INDEX('P&L Model'!B:B,MATCH(A16,'P&L Model'!A:A,0)) -> 123500 | C16: =B16*(1+$F$2)*(1+$G$2) -> 99726.25 | D16: =INDEX('P&L Model'!D:D,MATCH(A16,'P&L Model'!A:A,0)) -> 87200 | E16: =D16*(1+$H$2) -> 94176 | F16: =C16-E16 -> 5550.25 | G16: =INDEX('P&L Model'!J:J,MATCH(A16,'P&L Model'!A:A,0)) -> 641.67 | H16: =F16-G16 -> 4908.58 | I16: =Assumptions!$C$3 -> 833.33 | J16: =INDEX('Cashflow Forecast'!G:G,MATCH(A16,'Cashflow Forecast'!A:A,0)) -> -1200 | K16: =H16+I16+J16 -> 4541.91
A17: Apr | B17: =INDEX('P&L Model'!B:B,MATCH(A17,'P&L Model'!A:A,0)) -> 105600 | C17: =B17*(1+$F$2)*(1+$G$2) -> 85272 | D17: =INDEX('P&L Model'!D:D,MATCH(A17,'P&L Model'!A:A,0)) -> 87600 | E17: =D17*(1+$H$2) -> 94608 | F17: =C17-E17 -> -9336 | G17: =INDEX('P&L Model'!J:J,MATCH(A17,'P&L Model'!A:A,0)) -> 612.5 | H17: =F17-G17 -> -9948.5 | I17: =Assumptions!$C$3 -> 833.33 | J17: =INDEX('Cashflow Forecast'!G:G,MATCH(A17,'Cashflow Forecast'!A:A,0)) -> 1300 | K17: =H17+I17+J17 -> -7815.17
A18: May | B18: =INDEX('P&L Model'!B:B,MATCH(A18,'P&L Model'!A:A,0)) -> 134400 | C18: =B18*(1+$F$2)*(1+$G$2) -> 108528 | D18: =INDEX('P&L Model'!D:D,MATCH(A18,'P&L Model'!A:A,0)) -> 88500 | E18: =D18*(1+$H$2) -> 95580 | F18: =C18-E18 -> 12948 | G18: =INDEX('P&L Model'!J:J,MATCH(A18,'P&L Model'!A:A,0)) -> 583.33 | H18: =F18-G18 -> 12364.67 | I18: =Assumptions!$C$3 -> 833.33 | J18: =INDEX('Cashflow Forecast'!G:G,MATCH(A18,'Cashflow Forecast'!A:A,0)) -> -5200 | K18: =H18+I18+J18 -> 7998
A19: Jun | B19: =INDEX('P&L Model'!B:B,MATCH(A19,'P&L Model'!A:A,0)) -> 148800 | C19: =B19*(1+$F$2)*(1+$G$2) -> 120156 | D19: =INDEX('P&L Model'!D:D,MATCH(A19,'P&L Model'!A:A,0)) -> 89400 | E19: =D19*(1+$H$2) -> 96552 | F19: =C19-E19 -> 23604 | G19: =INDEX('P&L Model'!J:J,MATCH(A19,'P&L Model'!A:A,0)) -> 554.17 | H19: =F19-G19 -> 23049.83 | I19: =Assumptions!$C$3 -> 833.33 | J19: =INDEX('Cashflow Forecast'!G:G,MATCH(A19,'Cashflow Forecast'!A:A,0)) -> -2400 | K19: =H19+I19+J19 -> 21483.16
A20: Jul | B20: =INDEX('P&L Model'!B:B,MATCH(A20,'P&L Model'!A:A,0)) -> 160050 | C20: =B20*(1+$F$2)*(1+$G$2) -> 129240.38 | D20: =INDEX('P&L Model'!D:D,MATCH(A20,'P&L Model'!A:A,0)) -> 90300 | E20: =D20*(1+$H$2) -> 97524 | F20: =C20-E20 -> 31716.375 | G20: =INDEX('P&L Model'!J:J,MATCH(A20,'P&L Model'!A:A,0)) -> 525 | H20: =F20-G20 -> 31191.375 | I20: =Assumptions!$C$3 -> 833.33 | J20: =INDEX('Cashflow Forecast'!G:G,MATCH(A20,'Cashflow Forecast'!A:A,0)) -> -400 | K20: =H20+I20+J20 -> 31624.705
A21: Aug | B21: =INDEX('P&L Model'!B:B,MATCH(A21,'P&L Model'!A:A,0)) -> 164900 | C21: =B21*(1+$F$2)*(1+$G$2) -> 133156.75 | D21: =INDEX('P&L Model'!D:D,MATCH(A21,'P&L Model'!A:A,0)) -> 91200 | E21: =D21*(1+$H$2) -> 98496 | F21: =C21-E21 -> 34660.75 | G21: =INDEX('P&L Model'!J:J,MATCH(A21,'P&L Model'!A:A,0)) -> 495.83 | H21: =F21-G21 -> 34164.92 | I21: =Assumptions!$C$3 -> 833.33 | J21: =INDEX('Cashflow Forecast'!G:G,MATCH(A21,'Cashflow Forecast'!A:A,0)) -> -600 | K21: =H21+I21+J21 -> 34398.25
A22: Sep | B22: =INDEX('P&L Model'!B:B,MATCH(A22,'P&L Model'!A:A,0)) -> 156800 | C22: =B22*(1+$F$2)*(1+$G$2) -> 126616 | D22: =INDEX('P&L Model'!D:D,MATCH(A22,'P&L Model'!A:A,0)) -> 92100 | E22: =D22*(1+$H$2) -> 99468 | F22: =C22-E22 -> 27148 | G22: =INDEX('P&L Model'!J:J,MATCH(A22,'P&L Model'!A:A,0)) -> 466.67 | H22: =F22-G22 -> 26681.33 | I22: =Assumptions!$C$3 -> 833.33 | J22: =INDEX('Cashflow Forecast'!G:G,MATCH(A22,'Cashflow Forecast'!A:A,0)) -> -3000 | K22: =H22+I22+J22 -> 24514.66
A23: Oct | B23: =INDEX('P&L Model'!B:B,MATCH(A23,'P&L Model'!A:A,0)) -> 161700 | C23: =B23*(1+$F$2)*(1+$G$2) -> 130572.75 | D23: =INDEX('P&L Model'!D:D,MATCH(A23,'P&L Model'!A:A,0)) -> 92500 | E23: =D23*(1+$H$2) -> 99900 | F23: =C23-E23 -> 30672.75 | G23: =INDEX('P&L Model'!J:J,MATCH(A23,'P&L Model'!A:A,0)) -> 437.5 | H23: =F23-G23 -> 30235.25 | I23: =Assumptions!$C$3 -> 833.33 | J23: =INDEX('Cashflow Forecast'!G:G,MATCH(A23,'Cashflow Forecast'!A:A,0)) -> -1600 | K23: =H23+I23+J23 -> 29468.58
A24: Nov | B24: =INDEX('P&L Model'!B:B,MATCH(A24,'P&L Model'!A:A,0)) -> 178200 | C24: =B24*(1+$F$2)*(1+$G$2) -> 143896.5 | D24: =INDEX('P&L Model'!D:D,MATCH(A24,'P&L Model'!A:A,0)) -> 93400 | E24: =D24*(1+$H$2) -> 100872 | F24: =C24-E24 -> 43024.5 | G24: =INDEX('P&L Model'!J:J,MATCH(A24,'P&L Model'!A:A,0)) -> 408.33 | H24: =F24-G24 -> 42616.17 | I24: =Assumptions!$C$3 -> 833.33 | J24: =INDEX('Cashflow Forecast'!G:G,MATCH(A24,'Cashflow Forecast'!A:A,0)) -> -6600 | K24: =H24+I24+J24 -> 36849.5
A25: Dec | B25: =INDEX('P&L Model'!B:B,MATCH(A25,'P&L Model'!A:A,0)) -> 200000 | C25: =B25*(1+$F$2)*(1+$G$2) -> 161500 | D25: =INDEX('P&L Model'!D:D,MATCH(A25,'P&L Model'!A:A,0)) -> 94300 | E25: =D25*(1+$H$2) -> 101844 | F25: =C25-E25 -> 59656 | G25: =INDEX('P&L Model'!J:J,MATCH(A25,'P&L Model'!A:A,0)) -> 379.17 | H25: =F25-G25 -> 59276.83 | I25: =Assumptions!$C$3 -> 833.33 | J25: =INDEX('Cashflow Forecast'!G:G,MATCH(A25,'Cashflow Forecast'!A:A,0)) -> 2500 | K25: =H25+I25+J25 -> 62610.16

Sheet Cashflow Forecast
A1: Month | B1: Forecast Net Profit | C1: Depreciation | D1: Δreceivable | E1: Δpayable | F1: Δinventory | G1: WC net | H1: Foercast Operating Cashflow | I1: Forecast CAPEX | J1: Loan Principal | K1: Net cash move | L1: Opening cash | M1: Closing cash
A2: Jan | B2: =INDEX('P&L Model'!K:K,MATCH(A2,'P&L Model'!A:A, 0)) -> 27300 | C2: =Assumptions!$C$3 -> 833.33 | D2: 0 | E2: 0 | F2: 0 | G2: =-(D2)+(E2)-(F2) -> 0 | H2: =B2+C2+G2 -> 28133.33 | I2: =IFERROR(INDEX(CAPEX!B:B,MATCH(A2,CAPEX!A:A,0)),0) -> 0 | J2: =INDEX('Loan Schedule'!D:D,MATCH(A2,'Loan Schedule'!A:A,0)) -> 5000 | K2: =H2-I2-J2 -> 23133.33 | L2: =Assumptions!C2 -> 85000 | M2: =L2+K2 -> 108133.33
A3: Feb | B3: =INDEX('P&L Model'!K:K,MATCH(A3,'P&L Model'!A:A, 0)) -> 31729.17 | C3: =Assumptions!$C$3 -> 833.33 | D3: ='Working Capital'!B3-'Working Capital'!B2 -> 800 | E3: ='Working Capital'!C3-'Working Capital'!C2 -> 500 | F3: ='Working Capital'!D3-'Working Capital'!D2 -> 500 | G3: =-(D3)+(E3)-(F3) -> -800 | H3: =B3+C3+G3 -> 31762.5 | I3: =IFERROR(INDEX(CAPEX!B:B,MATCH(A3,CAPEX!A:A,0)),0) -> 0 | J3: =INDEX('Loan Schedule'!D:D,MATCH(A3,'Loan Schedule'!A:A,0)) -> 5000 | K3: =H3-I3-J3 -> 26762.5 | L3: =M2 -> 108133.33 | M3: =L3+K3 -> 134895.83
A4: Mar | B4: =INDEX('P&L Model'!K:K,MATCH(A4,'P&L Model'!A:A, 0)) -> 35658.33 | C4: =Assumptions!$C$3 -> 833.33 | D4: ='Working Capital'!B4-'Working Capital'!B3 -> 1200 | E4: ='Working Capital'!C4-'Working Capital'!C3 -> 500 | F4: ='Working Capital'!D4-'Working Capital'!D3 -> 500 | G4: =-(D4)+(E4)-(F4) -> -1200 | H4: =B4+C4+G4 -> 35291.66 | I4: =IFERROR(INDEX(CAPEX!B:B,MATCH(A4,CAPEX!A:A,0)),0) -> 25000 | J4: =INDEX('Loan Schedule'!D:D,MATCH(A4,'Loan Schedule'!A:A,0)) -> 5000 | K4: =H4-I4-J4 -> 5291.66 | L4: =M3 -> 134895.83 | M4: =L4+K4 -> 140187.49
A5: Apr | B5: =INDEX('P&L Model'!K:K,MATCH(A5,'P&L Model'!A:A, 0)) -> 17387.5 | C5: =Assumptions!$C$3 -> 833.33 | D5: ='Working Capital'!B5-'Working Capital'!B4 -> -800 | E5: ='Working Capital'!C5-'Working Capital'!C4 -> 1000 | F5: ='Working Capital'!D5-'Working Capital'!D4 -> 500 | G5: =-(D5)+(E5)-(F5) -> 1300 | H5: =B5+C5+G5 -> 19520.83 | I5: =IFERROR(INDEX(CAPEX!B:B,MATCH(A5,CAPEX!A:A,0)),0) -> 0 | J5: =INDEX('Loan Schedule'!D:D,MATCH(A5,'Loan Schedule'!A:A,0)) -> 5000 | K5: =H5-I5-J5 -> 14520.83 | L5: =M4 -> 140187.49 | M5: =L5+K5 -> 154708.32
A6: May | B6: =INDEX('P&L Model'!K:K,MATCH(A6,'P&L Model'!A:A, 0)) -> 45316.67 | C6: =Assumptions!$C$3 -> 833.33 | D6: ='Working Capital'!B6-'Working Capital'!B5 -> 2700 | E6: ='Working Capital'!C6-'Working Capital'!C5 -> 500 | F6: ='Working Capital'!D6-'Working Capital'!D5 -> 3000 | G6: =-(D6)+(E6)-(F6) -> -5200 | H6: =B6+C6+G6 -> 40950 | I6: =IFERROR(INDEX(CAPEX!B:B,MATCH(A6,CAPEX!A:A,0)),0) -> 0 | J6: =INDEX('Loan Schedule'!D:D,MATCH(A6,'Loan Schedule'!A:A,0)) -> 5000 | K6: =H6-I6-J6 -> 35950 | L6: =M5 -> 154708.32 | M6: =L6+K6 -> 190658.32
A7: Jun | B7: =INDEX('P&L Model'!K:K,MATCH(A7,'P&L Model'!A:A, 0)) -> 58845.83 | C7: =Assumptions!$C$3 -> 833.33 | D7: ='Working Capital'!B7-'Working Capital'!B6 -> 2400 | E7: ='Working Capital'!C7-'Working Capital'!C6 -> 500 | F7: ='Working Capital'!D7-'Working Capital'!D6 -> 500 | G7: =-(D7)+(E7)-(F7) -> -2400 | H7: =B7+C7+G7 -> 57279.16 | I7: =IFERROR(INDEX(CAPEX!B:B,MATCH(A7,CAPEX!A:A,0)),0) -> 0 | J7: =INDEX('Loan Schedule'!D:D,MATCH(A7,'Loan Schedule'!A:A,0)) -> 5000 | K7: =H7-I7-J7 -> 52279.16 | L7: =M6 -> 190658.32 | M7: =L7+K7 -> 242937.48
A8: Jul | B8: =INDEX('P&L Model'!K:K,MATCH(A8,'P&L Model'!A:A, 0)) -> 69225 | C8: =Assumptions!$C$3 -> 833.33 | D8: ='Working Capital'!B8-'Working Capital'!B7 -> 900 | E8: ='Working Capital'!C8-'Working Capital'!C7 -> 1000 | F8: ='Working Capital'!D8-'Working Capital'!D7 -> 500 | G8: =-(D8)+(E8)-(F8) -> -400 | H8: =B8+C8+G8 -> 69658.33 | I8: =IFERROR(INDEX(CAPEX!B:B,MATCH(A8,CAPEX!A:A,0)),0) -> 0 | J8: =INDEX('Loan Schedule'!D:D,MATCH(A8,'Loan Schedule'!A:A,0)) -> 5000 | K8: =H8-I8-J8 -> 64658.33 | L8: =M7 -> 242937.48 | M8: =L8+K8 -> 307595.81
A9: Aug | B9: =INDEX('P&L Model'!K:K,MATCH(A9,'P&L Model'!A:A, 0)) -> 73204.17 | C9: =Assumptions!$C$3 -> 833.33 | D9: ='Working Capital'!B9-'Working Capital'!B8 -> 1100 | E9: ='Working Capital'!C9-'Working Capital'!C8 -> 1000 | F9: ='Working Capital'!D9-'Working Capital'!D8 -> 500 | G9: =-(D9)+(E9)-(F9) -> -600 | H9: =B9+C9+G9 -> 73437.5 | I9: =IFERROR(INDEX(CAPEX!B:B,MATCH(A9,CAPEX!A:A,0)),0) -> 0 | J9: =INDEX('Loan Schedule'!D:D,MATCH(A9,'Loan Schedule'!A:A,0)) -> 5000 | K9: =H9-I9-J9 -> 68437.5 | L9: =M8 -> 307595.81 | M9: =L9+K9 -> 376033.31
A10: Sep | B10: =INDEX('P&L Model'!K:K,MATCH(A10,'P&L Model'!A:A, 0)) -> 64233.33 | C10: =Assumptions!$C$3 -> 833.33 | D10: ='Working Capital'!B10-'Working Capital'!B9 -> 1500 | E10: ='Working Capital'!C10-'Working Capital'!C9 -> 500 | F10: ='Working Capital'!D10-'Working Capital'!D9 -> 2000 | G10: =-(D10)+(E10)-(F10) -> -3000 | H10: =B10+C10+G10 -> 62066.66 | I10: =IFERROR(INDEX(CAPEX!B:B,MATCH(A10,CAPEX!A:A,0)),0) -> 30000 | J10: =INDEX('Loan Schedule'!D:D,MATCH(A10,'Loan Schedule'!A:A,0)) -> 5000 | K10: =H10-I10-J10 -> 27066.66 | L10: =M9 -> 376033.31 | M10: =L10+K10 -> 403099.97
A11: Oct | B11: =INDEX('P&L Model'!K:K,MATCH(A11,'P&L Model'!A:A, 0)) -> 68762.5 | C11: =Assumptions!$C$3 -> 833.33 | D11: ='Working Capital'!B11-'Working Capital'!B10 -> 1100 | E11: ='Working Capital'!C11-'Working Capital'!C10 -> 500 | F11: ='Working Capital'!D11-'Working Capital'!D10 -> 1000 | G11: =-(D11)+(E11)-(F11) -> -1600 | H11: =B11+C11+G11 -> 67995.83 | I11: =IFERROR(INDEX(CAPEX!B:B,MATCH(A11,CAPEX!A:A,0)),0) -> 0 | J11: =INDEX('Loan Schedule'!D:D,MATCH(A11,'Loan Schedule'!A:A,0)) -> 5000 | K11: =H11-I11-J11 -> 62995.83 | L11: =M10 -> 403099.97 | M11: =L11+K11 -> 466095.8
A12: Nov | B12: =INDEX('P&L Model'!K:K,MATCH(A12,'P&L Model'!A:A, 0)) -> 84391.67 | C12: =Assumptions!$C$3 -> 833.33 | D12: ='Working Capital'!B12-'Working Capital'!B11 -> 6100 | E12: ='Working Capital'!C12-'Working Capital'!C11 -> 500 | F12: ='Working Capital'!D12-'Working Capital'!D11 -> 1000 | G12: =-(D12)+(E12)-(F12) -> -6600 | H12: =B12+C12+G12 -> 78625 | I12: =IFERROR(INDEX(CAPEX!B:B,MATCH(A12,CAPEX!A:A,0)),0) -> 25000 | J12: =INDEX('Loan Schedule'!D:D,MATCH(A12,'Loan Schedule'!A:A,0)) -> 5000 | K12: =H12-I12-J12 -> 48625 | L12: =M11 -> 466095.8 | M12: =L12+K12 -> 514720.8
A13: Dec | B13: =INDEX('P&L Model'!K:K,MATCH(A13,'P&L Model'!A:A, 0)) -> 105320.83 | C13: =Assumptions!$C$3 -> 833.33 | D13: ='Working Capital'!B13-'Working Capital'!B12 -> -3000 | E13: ='Working Capital'!C13-'Working Capital'!C12 -> 500 | F13: ='Working Capital'!D13-'Working Capital'!D12 -> 1000 | G13: =-(D13)+(E13)-(F13) -> 2500 | H13: =B13+C13+G13 -> 108654.16 | I13: =IFERROR(INDEX(CAPEX!B:B,MATCH(A13,CAPEX!A:A,0)),0) -> 0 | J13: =INDEX('Loan Schedule'!D:D,MATCH(A13,'Loan Schedule'!A:A,0)) -> 5000 | K13: =H13-I13-J13 -> 103654.16 | L13: =M12 -> 514720.8 | M13: =L13+K13 -> 618374.96
